recall/__init__.py
recall/backends/__init__.py
recall/backends/qdrant.py
recall/chunking/__init__.py
recall/chunking/base.py
recall/chunking/factory.py
recall/chunking/json_chunker.py
recall/chunking/markdown.py
recall/chunking/prose.py
recall/chunking/python.py
recall/cli/__init__.py
recall/cli/cleanup.py
recall/cli/doctor.py
recall/cli/main.py
recall/cli/migrate.py
recall/cli/migrate_mode.py
recall/cli/recover.py
recall/cli/setup.py
recall/config/__init__.py
recall/config/loader.py
recall/core/__init__.py
recall/core/store.py
recall/embedders/__init__.py
recall/embedders/base.py
recall/embedders/mock.py
recall/embedders/ollama.py
recall/embedders/sentence_transformer.py
recall/mcp/__init__.py
recall/mcp/server.py
semantic_recall-1.4.1.dist-info/licenses/LICENSE
semantic_recall-1.4.1.dist-info/licenses/NOTICE
semantic_recall-1.4.1.dist-info/METADATA
semantic_recall-1.4.1.dist-info/WHEEL
semantic_recall-1.4.1.dist-info/entry_points.txt
semantic_recall-1.4.1.dist-info/top_level.txt
semantic_recall-1.4.1.dist-info/RECORD
